src/dcentralab-qa-automation/__init__.py
src/dcentralab-qa-automation/data/read_data.py
src/dcentralab-qa-automation/drivers/BraveDriver.py
src/dcentralab-qa-automation/drivers/ChromeDriver.py
src/dcentralab-qa-automation/fixtures/CreateTargetDirectory.py
src/dcentralab-qa-automation/fixtures/InitGlobalParameters.py
src/dcentralab-qa-automation/fixtures/Loggers.py
src/dcentralab-qa-automation/fixtures/OpenSiteWithCRXExtension.py
src/dcentralab-qa-automation/fixtures/ParameterInjection.py
src/dcentralab-qa-automation/fixtures/Screenshot.py
src/dcentralab-qa-automation/fixtures/SetupDriver.py
src/dcentralab-qa-automation/fixtures/SetupDriverWithMetamaskExtension.py
src/dcentralab-qa-automation/infra/CustomEventListener.py
src/dcentralab-qa-automation/utils/HTTPMethods.py
src/dcentralab-qa-automation/utils/WalletsActionsInterface.py
src/dcentralab-qa-automation/utils/enum/HTTPStatusCodes.py
src/dcentralab-qa-automation/utils/enum/NetworkTypes.py
src/dcentralab-qa-automation/utils/enum/Wallets.py
dcentralab_qa_automation-0.0.5.dist-info/METADATA
dcentralab_qa_automation-0.0.5.dist-info/WHEEL
dcentralab_qa_automation-0.0.5.dist-info/licenses/LICENSE
dcentralab_qa_automation-0.0.5.dist-info/RECORD
